bedrock_limiter_sdk.py
bedrock_limiter_sdk-1.0.0.dist-info/METADATA
bedrock_limiter_sdk-1.0.0.dist-info/WHEEL
bedrock_limiter_sdk-1.0.0.dist-info/top_level.txt
bedrock_limiter_sdk-1.0.0.dist-info/RECORD
