Metadata-Version: 2.4
Name: bedrock-limiter-sdk
Version: 1.0.0
Summary: Drop-in replacement for boto3 bedrock-runtime client with token limiting
Home-page: https://github.com/Tire-Rack-Innovation/token-limiter
Author: Tire Rack
Author-email: Tire Rack <dherthoge@tirerack.com>
License: MIT
Project-URL: Homepage, https://github.com/Tire-Rack-Innovation/token-limiter
Project-URL: Repository, https://github.com/Tire-Rack-Innovation/token-limiter
Project-URL: Documentation, https://github.com/Tire-Rack-Innovation/token-limiter/blob/main/docs/API_KEY_AUTHENTICATION.md
Keywords: aws,bedrock,boto3,token-limiting,rate-limiting
Requires-Python: >=3.8
Requires-Dist: boto3>=1.28.0
Requires-Dist: botocore>=1.31.0
Provides-Extra: dev
Requires-Dist: pytest>=7.0.0; extra == "dev"
Requires-Dist: black>=23.0.0; extra == "dev"
Requires-Dist: flake8>=6.0.0; extra == "dev"
Provides-Extra: langchain
Requires-Dist: langchain>=0.1.0; extra == "langchain"
Requires-Dist: langchain-aws>=0.1.0; extra == "langchain"
Dynamic: author
Dynamic: home-page
Dynamic: requires-python
